<?xml version="1.0" encoding="UTF-8" ?>
<!DOCTYPE mapper PUBLIC "-//mybatis.org//DTD Mapper 3.0//EN" "http://mybatis.org/dtd/mybatis-3-mapper.dtd" >
<mapper namespace="com.jason.mapper.ClassMapper" >
  <resultMap id="BaseResultMap" type="com.jason.model.Class" >
    <!--
      WARNING - @mbggenerated
      This element is automatically generated by MyBatis Generator, do not modify.
      This element was generated on Thu Apr 18 14:12:51 CST 2019.
    -->
    <id column="cno" property="cno" jdbcType="VARCHAR" />
    <result column="classrom" property="classrom" jdbcType="VARCHAR" />
    <result column="grade" property="grade" jdbcType="VARCHAR" />
    <result column="headmaster" property="headmaster" jdbcType="VARCHAR" />
    <result column="total_student" property="totalStudent" jdbcType="INTEGER" />
    <result column="major_id" property="majorId" jdbcType="INTEGER" />
  </resultMap>
  <sql id="Example_Where_Clause" >
    <!--
      WARNING - @mbggenerated
      This element is automatically generated by MyBatis Generator, do not modify.
      This element was generated on Thu Apr 18 14:12:51 CST 2019.
    -->
    <where >
      <foreach collection="oredCriteria" item="criteria" separator="or" >
        <if test="criteria.valid" >
          <trim prefix="(" suffix=")" prefixOverrides="and" >
            <foreach collection="criteria.criteria" item="criterion" >
              <choose >
                <when test="criterion.noValue" >
                  and ${criterion.condition}
                </when>
                <when test="criterion.singleValue" >
                  and ${criterion.condition} #{criterion.value}
                </when>
                <when test="criterion.betweenValue" >
                  and ${criterion.condition} #{criterion.value} and #{criterion.secondValue}
                </when>
                <when test="criterion.listValue" >
                  and ${criterion.condition}
                  <foreach collection="criterion.value" item="listItem" open="(" close=")" separator="," >
                    #{listItem}
                  </foreach>
                </when>
              </choose>
            </foreach>
          </trim>
        </if>
      </foreach>
    </where>
  </sql>
  <sql id="Update_By_Example_Where_Clause" >
    <!--
      WARNING - @mbggenerated
      This element is automatically generated by MyBatis Generator, do not modify.
      This element was generated on Thu Apr 18 14:12:51 CST 2019.
    -->
    <where >
      <foreach collection="example.oredCriteria" item="criteria" separator="or" >
        <if test="criteria.valid" >
          <trim prefix="(" suffix=")" prefixOverrides="and" >
            <foreach collection="criteria.criteria" item="criterion" >
              <choose >
                <when test="criterion.noValue" >
                  and ${criterion.condition}
                </when>
                <when test="criterion.singleValue" >
                  and ${criterion.condition} #{criterion.value}
                </when>
                <when test="criterion.betweenValue" >
                  and ${criterion.condition} #{criterion.value} and #{criterion.secondValue}
                </when>
                <when test="criterion.listValue" >
                  and ${criterion.condition}
                  <foreach collection="criterion.value" item="listItem" open="(" close=")" separator="," >
                    #{listItem}
                  </foreach>
                </when>
              </choose>
            </foreach>
          </trim>
        </if>
      </foreach>
    </where>
  </sql>
  <sql id="Base_Column_List" >
    <!--
      WARNING - @mbggenerated
      This element is automatically generated by MyBatis Generator, do not modify.
      This element was generated on Thu Apr 18 14:12:51 CST 2019.
    -->
    cno, classrom, grade, headmaster, total_student, major_id
  </sql>
  <select id="selectByExample" resultMap="BaseResultMap" parameterType="com.jason.model.ClassExample" >
    <!--
      WARNING - @mbggenerated
      This element is automatically generated by MyBatis Generator, do not modify.
      This element was generated on Thu Apr 18 14:12:51 CST 2019.
    -->
    select
    <if test="distinct" >
      distinct
    </if>
    <include refid="Base_Column_List" />
    from class
    <if test="_parameter != null" >
      <include refid="Example_Where_Clause" />
    </if>
    <if test="orderByClause != null" >
      order by ${orderByClause}
    </if>
  </select>
  <select id="selectByPrimaryKey" resultMap="BaseResultMap" parameterType="java.lang.String" >
    <!--
      WARNING - @mbggenerated
      This element is automatically generated by MyBatis Generator, do not modify.
      This element was generated on Thu Apr 18 14:12:51 CST 2019.
    -->
    select 
    <include refid="Base_Column_List" />
    from class
    where cno = #{cno,jdbcType=VARCHAR}
  </select>
  <delete id="deleteByPrimaryKey" parameterType="java.lang.String" >
    <!--
      WARNING - @mbggenerated
      This element is automatically generated by MyBatis Generator, do not modify.
      This element was generated on Thu Apr 18 14:12:51 CST 2019.
    -->
    delete from class
    where cno = #{cno,jdbcType=VARCHAR}
  </delete>
  <delete id="deleteByExample" parameterType="com.jason.model.ClassExample" >
    <!--
      WARNING - @mbggenerated
      This element is automatically generated by MyBatis Generator, do not modify.
      This element was generated on Thu Apr 18 14:12:51 CST 2019.
    -->
    delete from class
    <if test="_parameter != null" >
      <include refid="Example_Where_Clause" />
    </if>
  </delete>
  <insert id="insert" parameterType="com.jason.model.Class" >
    <!--
      WARNING - @mbggenerated
      This element is automatically generated by MyBatis Generator, do not modify.
      This element was generated on Thu Apr 18 14:12:51 CST 2019.
    -->
    insert into class (cno, classrom, grade, 
      headmaster, total_student, major_id
      )
    values (#{cno,jdbcType=VARCHAR}, #{classrom,jdbcType=VARCHAR}, #{grade,jdbcType=VARCHAR}, 
      #{headmaster,jdbcType=VARCHAR}, #{totalStudent,jdbcType=INTEGER}, #{majorId,jdbcType=INTEGER}
      )
  </insert>
  <insert id="insertSelective" parameterType="com.jason.model.Class" >
    <!--
      WARNING - @mbggenerated
      This element is automatically generated by MyBatis Generator, do not modify.
      This element was generated on Thu Apr 18 14:12:51 CST 2019.
    -->
    insert into class
    <trim prefix="(" suffix=")" suffixOverrides="," >
      <if test="cno != null" >
        cno,
      </if>
      <if test="classrom != null" >
        classrom,
      </if>
      <if test="grade != null" >
        grade,
      </if>
      <if test="headmaster != null" >
        headmaster,
      </if>
      <if test="totalStudent != null" >
        total_student,
      </if>
      <if test="majorId != null" >
        major_id,
      </if>
    </trim>
    <trim prefix="values (" suffix=")" suffixOverrides="," >
      <if test="cno != null" >
        #{cno,jdbcType=VARCHAR},
      </if>
      <if test="classrom != null" >
        #{classrom,jdbcType=VARCHAR},
      </if>
      <if test="grade != null" >
        #{grade,jdbcType=VARCHAR},
      </if>
      <if test="headmaster != null" >
        #{headmaster,jdbcType=VARCHAR},
      </if>
      <if test="totalStudent != null" >
        #{totalStudent,jdbcType=INTEGER},
      </if>
      <if test="majorId != null" >
        #{majorId,jdbcType=INTEGER},
      </if>
    </trim>
  </insert>
  <select id="countByExample" parameterType="com.jason.model.ClassExample" resultType="java.lang.Integer" >
    <!--
      WARNING - @mbggenerated
      This element is automatically generated by MyBatis Generator, do not modify.
      This element was generated on Thu Apr 18 14:12:51 CST 2019.
    -->
    select count(*) from class
    <if test="_parameter != null" >
      <include refid="Example_Where_Clause" />
    </if>
  </select>
  <update id="updateByExampleSelective" parameterType="map" >
    <!--
      WARNING - @mbggenerated
      This element is automatically generated by MyBatis Generator, do not modify.
      This element was generated on Thu Apr 18 14:12:51 CST 2019.
    -->
    update class
    <set >
      <if test="record.cno != null" >
        cno = #{record.cno,jdbcType=VARCHAR},
      </if>
      <if test="record.classrom != null" >
        classrom = #{record.classrom,jdbcType=VARCHAR},
      </if>
      <if test="record.grade != null" >
        grade = #{record.grade,jdbcType=VARCHAR},
      </if>
      <if test="record.headmaster != null" >
        headmaster = #{record.headmaster,jdbcType=VARCHAR},
      </if>
      <if test="record.totalStudent != null" >
        total_student = #{record.totalStudent,jdbcType=INTEGER},
      </if>
      <if test="record.majorId != null" >
        major_id = #{record.majorId,jdbcType=INTEGER},
      </if>
    </set>
    <if test="_parameter != null" >
      <include refid="Update_By_Example_Where_Clause" />
    </if>
  </update>
  <update id="updateByExample" parameterType="map" >
    <!--
      WARNING - @mbggenerated
      This element is automatically generated by MyBatis Generator, do not modify.
      This element was generated on Thu Apr 18 14:12:51 CST 2019.
    -->
    update class
    set cno = #{record.cno,jdbcType=VARCHAR},
      classrom = #{record.classrom,jdbcType=VARCHAR},
      grade = #{record.grade,jdbcType=VARCHAR},
      headmaster = #{record.headmaster,jdbcType=VARCHAR},
      total_student = #{record.totalStudent,jdbcType=INTEGER},
      major_id = #{record.majorId,jdbcType=INTEGER}
    <if test="_parameter != null" >
      <include refid="Update_By_Example_Where_Clause" />
    </if>
  </update>
  <update id="updateByPrimaryKeySelective" parameterType="com.jason.model.Class" >
    <!--
      WARNING - @mbggenerated
      This element is automatically generated by MyBatis Generator, do not modify.
      This element was generated on Thu Apr 18 14:12:51 CST 2019.
    -->
    update class
    <set >
      <if test="classrom != null" >
        classrom = #{classrom,jdbcType=VARCHAR},
      </if>
      <if test="grade != null" >
        grade = #{grade,jdbcType=VARCHAR},
      </if>
      <if test="headmaster != null" >
        headmaster = #{headmaster,jdbcType=VARCHAR},
      </if>
      <if test="totalStudent != null" >
        total_student = #{totalStudent,jdbcType=INTEGER},
      </if>
      <if test="majorId != null" >
        major_id = #{majorId,jdbcType=INTEGER},
      </if>
    </set>
    where cno = #{cno,jdbcType=VARCHAR}
  </update>
  <update id="updateByPrimaryKey" parameterType="com.jason.model.Class" >
    <!--
      WARNING - @mbggenerated
      This element is automatically generated by MyBatis Generator, do not modify.
      This element was generated on Thu Apr 18 14:12:51 CST 2019.
    -->
    update class
    set classrom = #{classrom,jdbcType=VARCHAR},
      grade = #{grade,jdbcType=VARCHAR},
      headmaster = #{headmaster,jdbcType=VARCHAR},
      total_student = #{totalStudent,jdbcType=INTEGER},
      major_id = #{majorId,jdbcType=INTEGER}
    where cno = #{cno,jdbcType=VARCHAR}
  </update>
</mapper>